lv_physics/__init__.py
lv_physics/core/__init__.py
lv_physics/core/catenaries.py
lv_physics/core/dynamic_objects.py
lv_physics/core/ohl_objects.py
lv_physics/core/rotations.py
lv_physics/core/scene_objects.py
lv_physics/core/vectors.py
lv_physics/dlr/__init__.py
lv_physics/dlr/const_objects.py
lv_physics/dlr/distributions.py
lv_physics/dlr/ieee_calcs.py
lv_physics/dlr/monte_carlo.py
lv_physics/dlr/monte_carlo_simulator.py
lv_physics/dlr/objects.py
lv_physics/dlr/simulation.py
lv_physics/dlr/thermalization.py
lv_physics/emf/__init__.py
lv_physics/emf/emf_const_objects.py
lv_physics/emf/emf_functions.py
lv_physics/emf/emf_objects.py
lv_physics/emf/helpers.py
lv_physics/general/__init__.py
lv_physics/general/objects.py
lv_physics/lidar/__init__.py
lv_physics/lidar/conductor_fitting.py
lv_physics/lidar/fitting_helpers.py
lv_physics/lidar/objects.py
lv_physics/lidar/point_cloud_calcs.py
lv_physics/utils/__init__.py
lv_physics/utils/dataclass_helpers.py
lv_physics/utils/helpers.py
lv_physics-0.3.1.dist-info/WHEEL
lv_physics-0.3.1.dist-info/METADATA
lv_physics-0.3.1.dist-info/RECORD
