Metadata-Version: 2.1
Name: lv_physics
Version: 0.3.1
Summary: A package for basic computational tools for LineVision specific physics and maths.
Author: B. Leist & J. Colston
Requires-Python: >=3.11
Requires-Dist: dataclasses-json
Requires-Dist: numpy
Requires-Dist: scipy
Requires-Dist: black ; extra == "dev"
Requires-Dist: ipython ; extra == "dev"
Requires-Dist: isort ; extra == "dev"
Requires-Dist: pre-commit ; extra == "dev"
Requires-Dist: python-lsp-server ; extra == "dev"
Requires-Dist: pytest ; extra == "dev"
Requires-Dist: twine ; extra == "dev"
Requires-Dist: wheel ; extra == "dev"
Provides-Extra: dev
